chess2vec/__init__.py
chess2vec/pgn.py
chess2vec/utils.py
chess2vec-1.0.2.dist-info/METADATA
chess2vec-1.0.2.dist-info/WHEEL
chess2vec-1.0.2.dist-info/RECORD
