Metadata-Version: 2.1
Name: chess2vec
Version: 1.0.2
Summary: 
Author: Piotr Żarczyński
Author-email: piotr.zarczynski.06@gmail.com
Requires-Python: >=3.10,<4.0
Classifier: Programming Language :: Python :: 3
Classifier: Programming Language :: Python :: 3.10
Classifier: Programming Language :: Python :: 3.11
Classifier: Programming Language :: Python :: 3.12
Requires-Dist: chess (>=1.10.0,<2.0.0)
Requires-Dist: numpy (>=1.26.4,<2.0.0)
Requires-Dist: pytest (>=8.1.1,<9.0.0)
Requires-Dist: tqdm (>=4.66.2,<5.0.0)
